igbot_rag/__init__.py
igbot_rag/chroma_vectorstore.py
igbot_rag/document_loader.py
igbot_rag/document_loader_2.py
igbot_rag/metadata_functions.py
igbot_rag-0.0.10.dist-info/METADATA
igbot_rag-0.0.10.dist-info/WHEEL
igbot_rag-0.0.10.dist-info/top_level.txt
igbot_rag-0.0.10.dist-info/RECORD
